cli/__init__.py
cli/chat.py
cli/config.py
cli/core.py
cli/logs.py
cli/manage.py
cli/models.py
llmhub_lib/__init__.py
llmhub_lib/actions.py
llmhub_lib/app_dependency_container.py
llmhub_lib/config_loader.py
llmhub_lib/config_manager.py
llmhub_lib/dependency_container.py
llmhub_lib/helpers.py
llmhub_lib/log_manager.py
llmhub_lib/model_manager.py
llmhub_lib/process_manager.py
llmhub_lib/service_manager.py
llmhub_lib/state_manager.py
llmhub_lib/web_server.py
llmhub_lib/model_extractor/__init__.py
llmhub_lib/model_extractor/generic_model_extractor.py
llmhub_lib/model_extractor/huggingface_model_extractor.py
llmhub_lib/model_extractor/utils.py
llmhub_cli-0.1.10.dist-info/METADATA
llmhub_cli-0.1.10.dist-info/WHEEL
llmhub_cli-0.1.10.dist-info/entry_points.txt
llmhub_cli-0.1.10.dist-info/top_level.txt
llmhub_cli-0.1.10.dist-info/RECORD
