Metadata-Version: 2.1
Name: llmhub-cli
Version: 0.1.10
Summary: LLMHub is a lightweight management platform designed to streamline working with LLMs.
Home-page: https://github.com/jmather/llmhub
Author: Jacob Mather
Author-email: jmather@jmather.com
Classifier: Programming Language :: Python :: 3
Classifier: License :: OSI Approved :: MIT License
Classifier: Operating System :: OS Independent
Requires-Python: >=3.6
Requires-Dist: flask
Requires-Dist: psutil
Requires-Dist: requests
Requires-Dist: click
Requires-Dist: PyYAML
